_tosa_checker_wrapper.cpython-310-x86_64-linux-gnu.so
tosa_checker-0.2.0.dist-info/LicenseRef-hwloc.txt
tosa_checker-0.2.0.dist-info/LGPL-2.1-or-later.txt
tosa_checker-0.2.0.dist-info/RECORD
tosa_checker-0.2.0.dist-info/BSD-2-Clause.txt
tosa_checker-0.2.0.dist-info/MPL-2.0.txt
tosa_checker-0.2.0.dist-info/LicenseRef-ARM_NEON_2_x86_SSE.txt
tosa_checker-0.2.0.dist-info/GPL-3.0-only.txt
tosa_checker-0.2.0.dist-info/Apache-2.0.txt
tosa_checker-0.2.0.dist-info/METADATA
tosa_checker-0.2.0.dist-info/LicenseRef-OouraFFT.txt
tosa_checker-0.2.0.dist-info/PSF-2.0.txt
tosa_checker-0.2.0.dist-info/WHEEL
tosa_checker-0.2.0.dist-info/GCC-exception-3.1.txt
tosa_checker-0.2.0.dist-info/BSD-3-Clause.txt
tosa_checker-0.2.0.dist-info/Zlib.txt
tosa_checker-0.2.0.dist-info/IJG.txt
tosa_checker-0.2.0.dist-info/MIT.txt
tosa_checker-0.2.0.dist-info/top_level.txt
tosa_checker-0.2.0.dist-info/LLVM-exception.txt
tosa_checker-0.2.0.dist-info/LICENSES.spdx
tosa_checker/__init__.py
