Metadata-Version: 2.1
Name: tosa-checker
Version: 0.2.0
Summary: Tool to check if a ML model is compatible with the TOSA specification
Home-page: https://git.mlplatform.org/tosa/tosa_checker.git/
Author: Arm Limited
License: Apache-2.0
Classifier: Development Status :: 3 - Alpha
Classifier: Intended Audience :: Developers
Classifier: License :: OSI Approved :: Apache Software License
Classifier: Programming Language :: Python :: 3
Classifier: Topic :: Utilities
Requires-Python: >=3.8
License-File: LICENSES.spdx
License-File: LICENSES/Apache-2.0.txt
License-File: LICENSES/BSD-2-Clause.txt
License-File: LICENSES/BSD-3-Clause.txt
License-File: LICENSES/GCC-exception-3.1.txt
License-File: LICENSES/GPL-3.0-only.txt
License-File: LICENSES/IJG.txt
License-File: LICENSES/LGPL-2.1-or-later.txt
License-File: LICENSES/LLVM-exception.txt
License-File: LICENSES/LicenseRef-ARM_NEON_2_x86_SSE.txt
License-File: LICENSES/LicenseRef-OouraFFT.txt
License-File: LICENSES/LicenseRef-hwloc.txt
License-File: LICENSES/MIT.txt
License-File: LICENSES/MPL-2.0.txt
License-File: LICENSES/PSF-2.0.txt
License-File: LICENSES/Zlib.txt
